package com.google.android.gms.internal;

import android.os.Binder;
import android.os.IBinder;
import android.os.IInterface;
import android.os.Parcel;
import android.os.Parcelable.Creator;
import android.os.RemoteException;
import com.google.firebase.auth.UserProfileChangeRequest;

public abstract interface zzbjb
  extends IInterface
{
  public abstract void zza(zzbja paramzzbja)
    throws RemoteException;
  
  public abstract void zza(zzbjz paramzzbjz, zzbja paramzzbja)
    throws RemoteException;
  
  public abstract void zza(String paramString, zzbja paramzzbja)
    throws RemoteException;
  
  public abstract void zza(String paramString, zzbjz paramzzbjz, zzbja paramzzbja)
    throws RemoteException;
  
  public abstract void zza(String paramString, UserProfileChangeRequest paramUserProfileChangeRequest, zzbja paramzzbja)
    throws RemoteException;
  
  public abstract void zza(String paramString1, String paramString2, zzbja paramzzbja)
    throws RemoteException;
  
  public abstract void zza(String paramString1, String paramString2, String paramString3, zzbja paramzzbja)
    throws RemoteException;
  
  public abstract void zzb(String paramString, zzbja paramzzbja)
    throws RemoteException;
  
  public abstract void zzb(String paramString1, String paramString2, zzbja paramzzbja)
    throws RemoteException;
  
  public abstract void zzc(String paramString, zzbja paramzzbja)
    throws RemoteException;
  
  public abstract void zzc(String paramString1, String paramString2, zzbja paramzzbja)
    throws RemoteException;
  
  public abstract void zzd(String paramString, zzbja paramzzbja)
    throws RemoteException;
  
  public abstract void zzd(String paramString1, String paramString2, zzbja paramzzbja)
    throws RemoteException;
  
  public abstract void zze(String paramString, zzbja paramzzbja)
    throws RemoteException;
  
  public abstract void zze(String paramString1, String paramString2, zzbja paramzzbja)
    throws RemoteException;
  
  public abstract void zzf(String paramString, zzbja paramzzbja)
    throws RemoteException;
  
  public abstract void zzf(String paramString1, String paramString2, zzbja paramzzbja)
    throws RemoteException;
  
  public abstract void zzg(String paramString, zzbja paramzzbja)
    throws RemoteException;
  
  public abstract void zzh(String paramString, zzbja paramzzbja)
    throws RemoteException;
  
  public abstract void zzi(String paramString, zzbja paramzzbja)
    throws RemoteException;
  
  public abstract void zzj(String paramString, zzbja paramzzbja)
    throws RemoteException;
  
  public static abstract class zza
    extends Binder
    implements zzbjb
  {
    public static zzbjb zzfE(IBinder paramIBinder)
    {
      if (paramIBinder == null) {
        return null;
      }
      IInterface localIInterface = paramIBinder.queryLocalInterface("com.google.firebase.auth.api.internal.IFirebaseAuthService");
      if ((localIInterface != null) && ((localIInterface instanceof zzbjb))) {
        return (zzbjb)localIInterface;
      }
      return new zza(paramIBinder);
    }
    
    public boolean onTransact(int paramInt1, Parcel paramParcel1, Parcel paramParcel2, int paramInt2)
      throws RemoteException
    {
      Object localObject = null;
      String str1 = null;
      String str2 = null;
      switch (paramInt1)
      {
      default: 
        return super.onTransact(paramInt1, paramParcel1, paramParcel2, paramInt2);
      case 1598968902: 
        paramParcel2.writeString("com.google.firebase.auth.api.internal.IFirebaseAuthService");
        return true;
      case 1: 
        paramParcel1.enforceInterface("com.google.firebase.auth.api.internal.IFirebaseAuthService");
        zza(paramParcel1.readString(), zzbja.zza.zzfD(paramParcel1.readStrongBinder()));
        paramParcel2.writeNoException();
        return true;
      case 2: 
        paramParcel1.enforceInterface("com.google.firebase.auth.api.internal.IFirebaseAuthService");
        zzb(paramParcel1.readString(), zzbja.zza.zzfD(paramParcel1.readStrongBinder()));
        paramParcel2.writeNoException();
        return true;
      case 3: 
        paramParcel1.enforceInterface("com.google.firebase.auth.api.internal.IFirebaseAuthService");
        localObject = str2;
        if (paramParcel1.readInt() != 0) {
          localObject = (zzbjz)zzbjz.CREATOR.createFromParcel(paramParcel1);
        }
        zza((zzbjz)localObject, zzbja.zza.zzfD(paramParcel1.readStrongBinder()));
        paramParcel2.writeNoException();
        return true;
      case 4: 
        paramParcel1.enforceInterface("com.google.firebase.auth.api.internal.IFirebaseAuthService");
        str1 = paramParcel1.readString();
        if (paramParcel1.readInt() != 0) {
          localObject = (UserProfileChangeRequest)UserProfileChangeRequest.CREATOR.createFromParcel(paramParcel1);
        }
        zza(str1, (UserProfileChangeRequest)localObject, zzbja.zza.zzfD(paramParcel1.readStrongBinder()));
        paramParcel2.writeNoException();
        return true;
      case 5: 
        paramParcel1.enforceInterface("com.google.firebase.auth.api.internal.IFirebaseAuthService");
        zza(paramParcel1.readString(), paramParcel1.readString(), zzbja.zza.zzfD(paramParcel1.readStrongBinder()));
        paramParcel2.writeNoException();
        return true;
      case 6: 
        paramParcel1.enforceInterface("com.google.firebase.auth.api.internal.IFirebaseAuthService");
        zzb(paramParcel1.readString(), paramParcel1.readString(), zzbja.zza.zzfD(paramParcel1.readStrongBinder()));
        paramParcel2.writeNoException();
        return true;
      case 7: 
        paramParcel1.enforceInterface("com.google.firebase.auth.api.internal.IFirebaseAuthService");
        zzc(paramParcel1.readString(), paramParcel1.readString(), zzbja.zza.zzfD(paramParcel1.readStrongBinder()));
        paramParcel2.writeNoException();
        return true;
      case 8: 
        paramParcel1.enforceInterface("com.google.firebase.auth.api.internal.IFirebaseAuthService");
        zzd(paramParcel1.readString(), paramParcel1.readString(), zzbja.zza.zzfD(paramParcel1.readStrongBinder()));
        paramParcel2.writeNoException();
        return true;
      case 9: 
        paramParcel1.enforceInterface("com.google.firebase.auth.api.internal.IFirebaseAuthService");
        zzc(paramParcel1.readString(), zzbja.zza.zzfD(paramParcel1.readStrongBinder()));
        paramParcel2.writeNoException();
        return true;
      case 10: 
        paramParcel1.enforceInterface("com.google.firebase.auth.api.internal.IFirebaseAuthService");
        zzd(paramParcel1.readString(), zzbja.zza.zzfD(paramParcel1.readStrongBinder()));
        paramParcel2.writeNoException();
        return true;
      case 11: 
        paramParcel1.enforceInterface("com.google.firebase.auth.api.internal.IFirebaseAuthService");
        zza(paramParcel1.readString(), paramParcel1.readString(), paramParcel1.readString(), zzbja.zza.zzfD(paramParcel1.readStrongBinder()));
        paramParcel2.writeNoException();
        return true;
      case 12: 
        paramParcel1.enforceInterface("com.google.firebase.auth.api.internal.IFirebaseAuthService");
        str2 = paramParcel1.readString();
        localObject = str1;
        if (paramParcel1.readInt() != 0) {
          localObject = (zzbjz)zzbjz.CREATOR.createFromParcel(paramParcel1);
        }
        zza(str2, (zzbjz)localObject, zzbja.zza.zzfD(paramParcel1.readStrongBinder()));
        paramParcel2.writeNoException();
        return true;
      case 13: 
        paramParcel1.enforceInterface("com.google.firebase.auth.api.internal.IFirebaseAuthService");
        zze(paramParcel1.readString(), zzbja.zza.zzfD(paramParcel1.readStrongBinder()));
        paramParcel2.writeNoException();
        return true;
      case 14: 
        paramParcel1.enforceInterface("com.google.firebase.auth.api.internal.IFirebaseAuthService");
        zze(paramParcel1.readString(), paramParcel1.readString(), zzbja.zza.zzfD(paramParcel1.readStrongBinder()));
        paramParcel2.writeNoException();
        return true;
      case 15: 
        paramParcel1.enforceInterface("com.google.firebase.auth.api.internal.IFirebaseAuthService");
        zzf(paramParcel1.readString(), zzbja.zza.zzfD(paramParcel1.readStrongBinder()));
        paramParcel2.writeNoException();
        return true;
      case 16: 
        paramParcel1.enforceInterface("com.google.firebase.auth.api.internal.IFirebaseAuthService");
        zza(zzbja.zza.zzfD(paramParcel1.readStrongBinder()));
        paramParcel2.writeNoException();
        return true;
      case 17: 
        paramParcel1.enforceInterface("com.google.firebase.auth.api.internal.IFirebaseAuthService");
        zzg(paramParcel1.readString(), zzbja.zza.zzfD(paramParcel1.readStrongBinder()));
        paramParcel2.writeNoException();
        return true;
      case 18: 
        paramParcel1.enforceInterface("com.google.firebase.auth.api.internal.IFirebaseAuthService");
        zzh(paramParcel1.readString(), zzbja.zza.zzfD(paramParcel1.readStrongBinder()));
        paramParcel2.writeNoException();
        return true;
      case 19: 
        paramParcel1.enforceInterface("com.google.firebase.auth.api.internal.IFirebaseAuthService");
        zzi(paramParcel1.readString(), zzbja.zza.zzfD(paramParcel1.readStrongBinder()));
        paramParcel2.writeNoException();
        return true;
      case 20: 
        paramParcel1.enforceInterface("com.google.firebase.auth.api.internal.IFirebaseAuthService");
        zzj(paramParcel1.readString(), zzbja.zza.zzfD(paramParcel1.readStrongBinder()));
        paramParcel2.writeNoException();
        return true;
      }
      paramParcel1.enforceInterface("com.google.firebase.auth.api.internal.IFirebaseAuthService");
      zzf(paramParcel1.readString(), paramParcel1.readString(), zzbja.zza.zzfD(paramParcel1.readStrongBinder()));
      paramParcel2.writeNoException();
      return true;
    }
    
    private static class zza
      implements zzbjb
    {
      private IBinder zzrp;
      
      zza(IBinder paramIBinder)
      {
        this.zzrp = paramIBinder;
      }
      
      public IBinder asBinder()
      {
        return this.zzrp;
      }
      
      /* Error */
      public void zza(zzbja paramzzbja)
        throws RemoteException
      {
        // Byte code:
        //   0: invokestatic 30	android/os/Parcel:obtain	()Landroid/os/Parcel;
        //   3: astore_2
        //   4: invokestatic 30	android/os/Parcel:obtain	()Landroid/os/Parcel;
        //   7: astore_3
        //   8: aload_2
        //   9: ldc 32
        //   11: invokevirtual 36	android/os/Parcel:writeInterfaceToken	(Ljava/lang/String;)V
        //   14: aload_1
        //   15: ifnull +43 -> 58
        //   18: aload_1
        //   19: invokeinterface 40 1 0
        //   24: astore_1
        //   25: aload_2
        //   26: aload_1
        //   27: invokevirtual 43	android/os/Parcel:writeStrongBinder	(Landroid/os/IBinder;)V
        //   30: aload_0
        //   31: getfield 18	com/google/android/gms/internal/zzbjb$zza$zza:zzrp	Landroid/os/IBinder;
        //   34: bipush 16
        //   36: aload_2
        //   37: aload_3
        //   38: iconst_0
        //   39: invokeinterface 49 5 0
        //   44: pop
        //   45: aload_3
        //   46: invokevirtual 52	android/os/Parcel:readException	()V
        //   49: aload_3
        //   50: invokevirtual 55	android/os/Parcel:recycle	()V
        //   53: aload_2
        //   54: invokevirtual 55	android/os/Parcel:recycle	()V
        //   57: return
        //   58: aconst_null
        //   59: astore_1
        //   60: goto -35 -> 25
        //   63: astore_1
        //   64: aload_3
        //   65: invokevirtual 55	android/os/Parcel:recycle	()V
        //   68: aload_2
        //   69: invokevirtual 55	android/os/Parcel:recycle	()V
        //   72: aload_1
        //   73: athrow
        // Local variable table:
        //   start	length	slot	name	signature
        //   0	74	0	this	zza
        //   0	74	1	paramzzbja	zzbja
        //   3	66	2	localParcel1	Parcel
        //   7	58	3	localParcel2	Parcel
        // Exception table:
        //   from	to	target	type
        //   8	14	63	finally
        //   18	25	63	finally
        //   25	49	63	finally
      }
      
      public void zza(zzbjz paramzzbjz, zzbja paramzzbja)
        throws RemoteException
      {
        Parcel localParcel1 = Parcel.obtain();
        Parcel localParcel2 = Parcel.obtain();
        for (;;)
        {
          try
          {
            localParcel1.writeInterfaceToken("com.google.firebase.auth.api.internal.IFirebaseAuthService");
            if (paramzzbjz != null)
            {
              localParcel1.writeInt(1);
              paramzzbjz.writeToParcel(localParcel1, 0);
              if (paramzzbja != null)
              {
                paramzzbjz = paramzzbja.asBinder();
                localParcel1.writeStrongBinder(paramzzbjz);
                this.zzrp.transact(3, localParcel1, localParcel2, 0);
                localParcel2.readException();
              }
            }
            else
            {
              localParcel1.writeInt(0);
              continue;
            }
            paramzzbjz = null;
          }
          finally
          {
            localParcel2.recycle();
            localParcel1.recycle();
          }
        }
      }
      
      /* Error */
      public void zza(String paramString, zzbja paramzzbja)
        throws RemoteException
      {
        // Byte code:
        //   0: invokestatic 30	android/os/Parcel:obtain	()Landroid/os/Parcel;
        //   3: astore_3
        //   4: invokestatic 30	android/os/Parcel:obtain	()Landroid/os/Parcel;
        //   7: astore 4
        //   9: aload_3
        //   10: ldc 32
        //   12: invokevirtual 36	android/os/Parcel:writeInterfaceToken	(Ljava/lang/String;)V
        //   15: aload_3
        //   16: aload_1
        //   17: invokevirtual 71	android/os/Parcel:writeString	(Ljava/lang/String;)V
        //   20: aload_2
        //   21: ifnull +45 -> 66
        //   24: aload_2
        //   25: invokeinterface 40 1 0
        //   30: astore_1
        //   31: aload_3
        //   32: aload_1
        //   33: invokevirtual 43	android/os/Parcel:writeStrongBinder	(Landroid/os/IBinder;)V
        //   36: aload_0
        //   37: getfield 18	com/google/android/gms/internal/zzbjb$zza$zza:zzrp	Landroid/os/IBinder;
        //   40: iconst_1
        //   41: aload_3
        //   42: aload 4
        //   44: iconst_0
        //   45: invokeinterface 49 5 0
        //   50: pop
        //   51: aload 4
        //   53: invokevirtual 52	android/os/Parcel:readException	()V
        //   56: aload 4
        //   58: invokevirtual 55	android/os/Parcel:recycle	()V
        //   61: aload_3
        //   62: invokevirtual 55	android/os/Parcel:recycle	()V
        //   65: return
        //   66: aconst_null
        //   67: astore_1
        //   68: goto -37 -> 31
        //   71: astore_1
        //   72: aload 4
        //   74: invokevirtual 55	android/os/Parcel:recycle	()V
        //   77: aload_3
        //   78: invokevirtual 55	android/os/Parcel:recycle	()V
        //   81: aload_1
        //   82: athrow
        // Local variable table:
        //   start	length	slot	name	signature
        //   0	83	0	this	zza
        //   0	83	1	paramString	String
        //   0	83	2	paramzzbja	zzbja
        //   3	75	3	localParcel1	Parcel
        //   7	66	4	localParcel2	Parcel
        // Exception table:
        //   from	to	target	type
        //   9	20	71	finally
        //   24	31	71	finally
        //   31	56	71	finally
      }
      
      public void zza(String paramString, zzbjz paramzzbjz, zzbja paramzzbja)
        throws RemoteException
      {
        Parcel localParcel1 = Parcel.obtain();
        Parcel localParcel2 = Parcel.obtain();
        for (;;)
        {
          try
          {
            localParcel1.writeInterfaceToken("com.google.firebase.auth.api.internal.IFirebaseAuthService");
            localParcel1.writeString(paramString);
            if (paramzzbjz != null)
            {
              localParcel1.writeInt(1);
              paramzzbjz.writeToParcel(localParcel1, 0);
              if (paramzzbja != null)
              {
                paramString = paramzzbja.asBinder();
                localParcel1.writeStrongBinder(paramString);
                this.zzrp.transact(12, localParcel1, localParcel2, 0);
                localParcel2.readException();
              }
            }
            else
            {
              localParcel1.writeInt(0);
              continue;
            }
            paramString = null;
          }
          finally
          {
            localParcel2.recycle();
            localParcel1.recycle();
          }
        }
      }
      
      public void zza(String paramString, UserProfileChangeRequest paramUserProfileChangeRequest, zzbja paramzzbja)
        throws RemoteException
      {
        Parcel localParcel1 = Parcel.obtain();
        Parcel localParcel2 = Parcel.obtain();
        for (;;)
        {
          try
          {
            localParcel1.writeInterfaceToken("com.google.firebase.auth.api.internal.IFirebaseAuthService");
            localParcel1.writeString(paramString);
            if (paramUserProfileChangeRequest != null)
            {
              localParcel1.writeInt(1);
              paramUserProfileChangeRequest.writeToParcel(localParcel1, 0);
              if (paramzzbja != null)
              {
                paramString = paramzzbja.asBinder();
                localParcel1.writeStrongBinder(paramString);
                this.zzrp.transact(4, localParcel1, localParcel2, 0);
                localParcel2.readException();
              }
            }
            else
            {
              localParcel1.writeInt(0);
              continue;
            }
            paramString = null;
          }
          finally
          {
            localParcel2.recycle();
            localParcel1.recycle();
          }
        }
      }
      
      /* Error */
      public void zza(String paramString1, String paramString2, zzbja paramzzbja)
        throws RemoteException
      {
        // Byte code:
        //   0: invokestatic 30	android/os/Parcel:obtain	()Landroid/os/Parcel;
        //   3: astore 4
        //   5: invokestatic 30	android/os/Parcel:obtain	()Landroid/os/Parcel;
        //   8: astore 5
        //   10: aload 4
        //   12: ldc 32
        //   14: invokevirtual 36	android/os/Parcel:writeInterfaceToken	(Ljava/lang/String;)V
        //   17: aload 4
        //   19: aload_1
        //   20: invokevirtual 71	android/os/Parcel:writeString	(Ljava/lang/String;)V
        //   23: aload 4
        //   25: aload_2
        //   26: invokevirtual 71	android/os/Parcel:writeString	(Ljava/lang/String;)V
        //   29: aload_3
        //   30: ifnull +48 -> 78
        //   33: aload_3
        //   34: invokeinterface 40 1 0
        //   39: astore_1
        //   40: aload 4
        //   42: aload_1
        //   43: invokevirtual 43	android/os/Parcel:writeStrongBinder	(Landroid/os/IBinder;)V
        //   46: aload_0
        //   47: getfield 18	com/google/android/gms/internal/zzbjb$zza$zza:zzrp	Landroid/os/IBinder;
        //   50: iconst_5
        //   51: aload 4
        //   53: aload 5
        //   55: iconst_0
        //   56: invokeinterface 49 5 0
        //   61: pop
        //   62: aload 5
        //   64: invokevirtual 52	android/os/Parcel:readException	()V
        //   67: aload 5
        //   69: invokevirtual 55	android/os/Parcel:recycle	()V
        //   72: aload 4
        //   74: invokevirtual 55	android/os/Parcel:recycle	()V
        //   77: return
        //   78: aconst_null
        //   79: astore_1
        //   80: goto -40 -> 40
        //   83: astore_1
        //   84: aload 5
        //   86: invokevirtual 55	android/os/Parcel:recycle	()V
        //   89: aload 4
        //   91: invokevirtual 55	android/os/Parcel:recycle	()V
        //   94: aload_1
        //   95: athrow
        // Local variable table:
        //   start	length	slot	name	signature
        //   0	96	0	this	zza
        //   0	96	1	paramString1	String
        //   0	96	2	paramString2	String
        //   0	96	3	paramzzbja	zzbja
        //   3	87	4	localParcel1	Parcel
        //   8	77	5	localParcel2	Parcel
        // Exception table:
        //   from	to	target	type
        //   10	29	83	finally
        //   33	40	83	finally
        //   40	67	83	finally
      }
      
      /* Error */
      public void zza(String paramString1, String paramString2, String paramString3, zzbja paramzzbja)
        throws RemoteException
      {
        // Byte code:
        //   0: invokestatic 30	android/os/Parcel:obtain	()Landroid/os/Parcel;
        //   3: astore 5
        //   5: invokestatic 30	android/os/Parcel:obtain	()Landroid/os/Parcel;
        //   8: astore 6
        //   10: aload 5
        //   12: ldc 32
        //   14: invokevirtual 36	android/os/Parcel:writeInterfaceToken	(Ljava/lang/String;)V
        //   17: aload 5
        //   19: aload_1
        //   20: invokevirtual 71	android/os/Parcel:writeString	(Ljava/lang/String;)V
        //   23: aload 5
        //   25: aload_2
        //   26: invokevirtual 71	android/os/Parcel:writeString	(Ljava/lang/String;)V
        //   29: aload 5
        //   31: aload_3
        //   32: invokevirtual 71	android/os/Parcel:writeString	(Ljava/lang/String;)V
        //   35: aload 4
        //   37: ifnull +50 -> 87
        //   40: aload 4
        //   42: invokeinterface 40 1 0
        //   47: astore_1
        //   48: aload 5
        //   50: aload_1
        //   51: invokevirtual 43	android/os/Parcel:writeStrongBinder	(Landroid/os/IBinder;)V
        //   54: aload_0
        //   55: getfield 18	com/google/android/gms/internal/zzbjb$zza$zza:zzrp	Landroid/os/IBinder;
        //   58: bipush 11
        //   60: aload 5
        //   62: aload 6
        //   64: iconst_0
        //   65: invokeinterface 49 5 0
        //   70: pop
        //   71: aload 6
        //   73: invokevirtual 52	android/os/Parcel:readException	()V
        //   76: aload 6
        //   78: invokevirtual 55	android/os/Parcel:recycle	()V
        //   81: aload 5
        //   83: invokevirtual 55	android/os/Parcel:recycle	()V
        //   86: return
        //   87: aconst_null
        //   88: astore_1
        //   89: goto -41 -> 48
        //   92: astore_1
        //   93: aload 6
        //   95: invokevirtual 55	android/os/Parcel:recycle	()V
        //   98: aload 5
        //   100: invokevirtual 55	android/os/Parcel:recycle	()V
        //   103: aload_1
        //   104: athrow
        // Local variable table:
        //   start	length	slot	name	signature
        //   0	105	0	this	zza
        //   0	105	1	paramString1	String
        //   0	105	2	paramString2	String
        //   0	105	3	paramString3	String
        //   0	105	4	paramzzbja	zzbja
        //   3	96	5	localParcel1	Parcel
        //   8	86	6	localParcel2	Parcel
        // Exception table:
        //   from	to	target	type
        //   10	35	92	finally
        //   40	48	92	finally
        //   48	76	92	finally
      }
      
      /* Error */
      public void zzb(String paramString, zzbja paramzzbja)
        throws RemoteException
      {
        // Byte code:
        //   0: invokestatic 30	android/os/Parcel:obtain	()Landroid/os/Parcel;
        //   3: astore_3
        //   4: invokestatic 30	android/os/Parcel:obtain	()Landroid/os/Parcel;
        //   7: astore 4
        //   9: aload_3
        //   10: ldc 32
        //   12: invokevirtual 36	android/os/Parcel:writeInterfaceToken	(Ljava/lang/String;)V
        //   15: aload_3
        //   16: aload_1
        //   17: invokevirtual 71	android/os/Parcel:writeString	(Ljava/lang/String;)V
        //   20: aload_2
        //   21: ifnull +45 -> 66
        //   24: aload_2
        //   25: invokeinterface 40 1 0
        //   30: astore_1
        //   31: aload_3
        //   32: aload_1
        //   33: invokevirtual 43	android/os/Parcel:writeStrongBinder	(Landroid/os/IBinder;)V
        //   36: aload_0
        //   37: getfield 18	com/google/android/gms/internal/zzbjb$zza$zza:zzrp	Landroid/os/IBinder;
        //   40: iconst_2
        //   41: aload_3
        //   42: aload 4
        //   44: iconst_0
        //   45: invokeinterface 49 5 0
        //   50: pop
        //   51: aload 4
        //   53: invokevirtual 52	android/os/Parcel:readException	()V
        //   56: aload 4
        //   58: invokevirtual 55	android/os/Parcel:recycle	()V
        //   61: aload_3
        //   62: invokevirtual 55	android/os/Parcel:recycle	()V
        //   65: return
        //   66: aconst_null
        //   67: astore_1
        //   68: goto -37 -> 31
        //   71: astore_1
        //   72: aload 4
        //   74: invokevirtual 55	android/os/Parcel:recycle	()V
        //   77: aload_3
        //   78: invokevirtual 55	android/os/Parcel:recycle	()V
        //   81: aload_1
        //   82: athrow
        // Local variable table:
        //   start	length	slot	name	signature
        //   0	83	0	this	zza
        //   0	83	1	paramString	String
        //   0	83	2	paramzzbja	zzbja
        //   3	75	3	localParcel1	Parcel
        //   7	66	4	localParcel2	Parcel
        // Exception table:
        //   from	to	target	type
        //   9	20	71	finally
        //   24	31	71	finally
        //   31	56	71	finally
      }
      
      /* Error */
      public void zzb(String paramString1, String paramString2, zzbja paramzzbja)
        throws RemoteException
      {
        // Byte code:
        //   0: invokestatic 30	android/os/Parcel:obtain	()Landroid/os/Parcel;
        //   3: astore 4
        //   5: invokestatic 30	android/os/Parcel:obtain	()Landroid/os/Parcel;
        //   8: astore 5
        //   10: aload 4
        //   12: ldc 32
        //   14: invokevirtual 36	android/os/Parcel:writeInterfaceToken	(Ljava/lang/String;)V
        //   17: aload 4
        //   19: aload_1
        //   20: invokevirtual 71	android/os/Parcel:writeString	(Ljava/lang/String;)V
        //   23: aload 4
        //   25: aload_2
        //   26: invokevirtual 71	android/os/Parcel:writeString	(Ljava/lang/String;)V
        //   29: aload_3
        //   30: ifnull +49 -> 79
        //   33: aload_3
        //   34: invokeinterface 40 1 0
        //   39: astore_1
        //   40: aload 4
        //   42: aload_1
        //   43: invokevirtual 43	android/os/Parcel:writeStrongBinder	(Landroid/os/IBinder;)V
        //   46: aload_0
        //   47: getfield 18	com/google/android/gms/internal/zzbjb$zza$zza:zzrp	Landroid/os/IBinder;
        //   50: bipush 6
        //   52: aload 4
        //   54: aload 5
        //   56: iconst_0
        //   57: invokeinterface 49 5 0
        //   62: pop
        //   63: aload 5
        //   65: invokevirtual 52	android/os/Parcel:readException	()V
        //   68: aload 5
        //   70: invokevirtual 55	android/os/Parcel:recycle	()V
        //   73: aload 4
        //   75: invokevirtual 55	android/os/Parcel:recycle	()V
        //   78: return
        //   79: aconst_null
        //   80: astore_1
        //   81: goto -41 -> 40
        //   84: astore_1
        //   85: aload 5
        //   87: invokevirtual 55	android/os/Parcel:recycle	()V
        //   90: aload 4
        //   92: invokevirtual 55	android/os/Parcel:recycle	()V
        //   95: aload_1
        //   96: athrow
        // Local variable table:
        //   start	length	slot	name	signature
        //   0	97	0	this	zza
        //   0	97	1	paramString1	String
        //   0	97	2	paramString2	String
        //   0	97	3	paramzzbja	zzbja
        //   3	88	4	localParcel1	Parcel
        //   8	78	5	localParcel2	Parcel
        // Exception table:
        //   from	to	target	type
        //   10	29	84	finally
        //   33	40	84	finally
        //   40	68	84	finally
      }
      
      /* Error */
      public void zzc(String paramString, zzbja paramzzbja)
        throws RemoteException
      {
        // Byte code:
        //   0: invokestatic 30	android/os/Parcel:obtain	()Landroid/os/Parcel;
        //   3: astore_3
        //   4: invokestatic 30	android/os/Parcel:obtain	()Landroid/os/Parcel;
        //   7: astore 4
        //   9: aload_3
        //   10: ldc 32
        //   12: invokevirtual 36	android/os/Parcel:writeInterfaceToken	(Ljava/lang/String;)V
        //   15: aload_3
        //   16: aload_1
        //   17: invokevirtual 71	android/os/Parcel:writeString	(Ljava/lang/String;)V
        //   20: aload_2
        //   21: ifnull +46 -> 67
        //   24: aload_2
        //   25: invokeinterface 40 1 0
        //   30: astore_1
        //   31: aload_3
        //   32: aload_1
        //   33: invokevirtual 43	android/os/Parcel:writeStrongBinder	(Landroid/os/IBinder;)V
        //   36: aload_0
        //   37: getfield 18	com/google/android/gms/internal/zzbjb$zza$zza:zzrp	Landroid/os/IBinder;
        //   40: bipush 9
        //   42: aload_3
        //   43: aload 4
        //   45: iconst_0
        //   46: invokeinterface 49 5 0
        //   51: pop
        //   52: aload 4
        //   54: invokevirtual 52	android/os/Parcel:readException	()V
        //   57: aload 4
        //   59: invokevirtual 55	android/os/Parcel:recycle	()V
        //   62: aload_3
        //   63: invokevirtual 55	android/os/Parcel:recycle	()V
        //   66: return
        //   67: aconst_null
        //   68: astore_1
        //   69: goto -38 -> 31
        //   72: astore_1
        //   73: aload 4
        //   75: invokevirtual 55	android/os/Parcel:recycle	()V
        //   78: aload_3
        //   79: invokevirtual 55	android/os/Parcel:recycle	()V
        //   82: aload_1
        //   83: athrow
        // Local variable table:
        //   start	length	slot	name	signature
        //   0	84	0	this	zza
        //   0	84	1	paramString	String
        //   0	84	2	paramzzbja	zzbja
        //   3	76	3	localParcel1	Parcel
        //   7	67	4	localParcel2	Parcel
        // Exception table:
        //   from	to	target	type
        //   9	20	72	finally
        //   24	31	72	finally
        //   31	57	72	finally
      }
      
      /* Error */
      public void zzc(String paramString1, String paramString2, zzbja paramzzbja)
        throws RemoteException
      {
        // Byte code:
        //   0: invokestatic 30	android/os/Parcel:obtain	()Landroid/os/Parcel;
        //   3: astore 4
        //   5: invokestatic 30	android/os/Parcel:obtain	()Landroid/os/Parcel;
        //   8: astore 5
        //   10: aload 4
        //   12: ldc 32
        //   14: invokevirtual 36	android/os/Parcel:writeInterfaceToken	(Ljava/lang/String;)V
        //   17: aload 4
        //   19: aload_1
        //   20: invokevirtual 71	android/os/Parcel:writeString	(Ljava/lang/String;)V
        //   23: aload 4
        //   25: aload_2
        //   26: invokevirtual 71	android/os/Parcel:writeString	(Ljava/lang/String;)V
        //   29: aload_3
        //   30: ifnull +49 -> 79
        //   33: aload_3
        //   34: invokeinterface 40 1 0
        //   39: astore_1
        //   40: aload 4
        //   42: aload_1
        //   43: invokevirtual 43	android/os/Parcel:writeStrongBinder	(Landroid/os/IBinder;)V
        //   46: aload_0
        //   47: getfield 18	com/google/android/gms/internal/zzbjb$zza$zza:zzrp	Landroid/os/IBinder;
        //   50: bipush 7
        //   52: aload 4
        //   54: aload 5
        //   56: iconst_0
        //   57: invokeinterface 49 5 0
        //   62: pop
        //   63: aload 5
        //   65: invokevirtual 52	android/os/Parcel:readException	()V
        //   68: aload 5
        //   70: invokevirtual 55	android/os/Parcel:recycle	()V
        //   73: aload 4
        //   75: invokevirtual 55	android/os/Parcel:recycle	()V
        //   78: return
        //   79: aconst_null
        //   80: astore_1
        //   81: goto -41 -> 40
        //   84: astore_1
        //   85: aload 5
        //   87: invokevirtual 55	android/os/Parcel:recycle	()V
        //   90: aload 4
        //   92: invokevirtual 55	android/os/Parcel:recycle	()V
        //   95: aload_1
        //   96: athrow
        // Local variable table:
        //   start	length	slot	name	signature
        //   0	97	0	this	zza
        //   0	97	1	paramString1	String
        //   0	97	2	paramString2	String
        //   0	97	3	paramzzbja	zzbja
        //   3	88	4	localParcel1	Parcel
        //   8	78	5	localParcel2	Parcel
        // Exception table:
        //   from	to	target	type
        //   10	29	84	finally
        //   33	40	84	finally
        //   40	68	84	finally
      }
      
      /* Error */
      public void zzd(String paramString, zzbja paramzzbja)
        throws RemoteException
      {
        // Byte code:
        //   0: invokestatic 30	android/os/Parcel:obtain	()Landroid/os/Parcel;
        //   3: astore_3
        //   4: invokestatic 30	android/os/Parcel:obtain	()Landroid/os/Parcel;
        //   7: astore 4
        //   9: aload_3
        //   10: ldc 32
        //   12: invokevirtual 36	android/os/Parcel:writeInterfaceToken	(Ljava/lang/String;)V
        //   15: aload_3
        //   16: aload_1
        //   17: invokevirtual 71	android/os/Parcel:writeString	(Ljava/lang/String;)V
        //   20: aload_2
        //   21: ifnull +46 -> 67
        //   24: aload_2
        //   25: invokeinterface 40 1 0
        //   30: astore_1
        //   31: aload_3
        //   32: aload_1
        //   33: invokevirtual 43	android/os/Parcel:writeStrongBinder	(Landroid/os/IBinder;)V
        //   36: aload_0
        //   37: getfield 18	com/google/android/gms/internal/zzbjb$zza$zza:zzrp	Landroid/os/IBinder;
        //   40: bipush 10
        //   42: aload_3
        //   43: aload 4
        //   45: iconst_0
        //   46: invokeinterface 49 5 0
        //   51: pop
        //   52: aload 4
        //   54: invokevirtual 52	android/os/Parcel:readException	()V
        //   57: aload 4
        //   59: invokevirtual 55	android/os/Parcel:recycle	()V
        //   62: aload_3
        //   63: invokevirtual 55	android/os/Parcel:recycle	()V
        //   66: return
        //   67: aconst_null
        //   68: astore_1
        //   69: goto -38 -> 31
        //   72: astore_1
        //   73: aload 4
        //   75: invokevirtual 55	android/os/Parcel:recycle	()V
        //   78: aload_3
        //   79: invokevirtual 55	android/os/Parcel:recycle	()V
        //   82: aload_1
        //   83: athrow
        // Local variable table:
        //   start	length	slot	name	signature
        //   0	84	0	this	zza
        //   0	84	1	paramString	String
        //   0	84	2	paramzzbja	zzbja
        //   3	76	3	localParcel1	Parcel
        //   7	67	4	localParcel2	Parcel
        // Exception table:
        //   from	to	target	type
        //   9	20	72	finally
        //   24	31	72	finally
        //   31	57	72	finally
      }
      
      /* Error */
      public void zzd(String paramString1, String paramString2, zzbja paramzzbja)
        throws RemoteException
      {
        // Byte code:
        //   0: invokestatic 30	android/os/Parcel:obtain	()Landroid/os/Parcel;
        //   3: astore 4
        //   5: invokestatic 30	android/os/Parcel:obtain	()Landroid/os/Parcel;
        //   8: astore 5
        //   10: aload 4
        //   12: ldc 32
        //   14: invokevirtual 36	android/os/Parcel:writeInterfaceToken	(Ljava/lang/String;)V
        //   17: aload 4
        //   19: aload_1
        //   20: invokevirtual 71	android/os/Parcel:writeString	(Ljava/lang/String;)V
        //   23: aload 4
        //   25: aload_2
        //   26: invokevirtual 71	android/os/Parcel:writeString	(Ljava/lang/String;)V
        //   29: aload_3
        //   30: ifnull +49 -> 79
        //   33: aload_3
        //   34: invokeinterface 40 1 0
        //   39: astore_1
        //   40: aload 4
        //   42: aload_1
        //   43: invokevirtual 43	android/os/Parcel:writeStrongBinder	(Landroid/os/IBinder;)V
        //   46: aload_0
        //   47: getfield 18	com/google/android/gms/internal/zzbjb$zza$zza:zzrp	Landroid/os/IBinder;
        //   50: bipush 8
        //   52: aload 4
        //   54: aload 5
        //   56: iconst_0
        //   57: invokeinterface 49 5 0
        //   62: pop
        //   63: aload 5
        //   65: invokevirtual 52	android/os/Parcel:readException	()V
        //   68: aload 5
        //   70: invokevirtual 55	android/os/Parcel:recycle	()V
        //   73: aload 4
        //   75: invokevirtual 55	android/os/Parcel:recycle	()V
        //   78: return
        //   79: aconst_null
        //   80: astore_1
        //   81: goto -41 -> 40
        //   84: astore_1
        //   85: aload 5
        //   87: invokevirtual 55	android/os/Parcel:recycle	()V
        //   90: aload 4
        //   92: invokevirtual 55	android/os/Parcel:recycle	()V
        //   95: aload_1
        //   96: athrow
        // Local variable table:
        //   start	length	slot	name	signature
        //   0	97	0	this	zza
        //   0	97	1	paramString1	String
        //   0	97	2	paramString2	String
        //   0	97	3	paramzzbja	zzbja
        //   3	88	4	localParcel1	Parcel
        //   8	78	5	localParcel2	Parcel
        // Exception table:
        //   from	to	target	type
        //   10	29	84	finally
        //   33	40	84	finally
        //   40	68	84	finally
      }
      
      /* Error */
      public void zze(String paramString, zzbja paramzzbja)
        throws RemoteException
      {
        // Byte code:
        //   0: invokestatic 30	android/os/Parcel:obtain	()Landroid/os/Parcel;
        //   3: astore_3
        //   4: invokestatic 30	android/os/Parcel:obtain	()Landroid/os/Parcel;
        //   7: astore 4
        //   9: aload_3
        //   10: ldc 32
        //   12: invokevirtual 36	android/os/Parcel:writeInterfaceToken	(Ljava/lang/String;)V
        //   15: aload_3
        //   16: aload_1
        //   17: invokevirtual 71	android/os/Parcel:writeString	(Ljava/lang/String;)V
        //   20: aload_2
        //   21: ifnull +46 -> 67
        //   24: aload_2
        //   25: invokeinterface 40 1 0
        //   30: astore_1
        //   31: aload_3
        //   32: aload_1
        //   33: invokevirtual 43	android/os/Parcel:writeStrongBinder	(Landroid/os/IBinder;)V
        //   36: aload_0
        //   37: getfield 18	com/google/android/gms/internal/zzbjb$zza$zza:zzrp	Landroid/os/IBinder;
        //   40: bipush 13
        //   42: aload_3
        //   43: aload 4
        //   45: iconst_0
        //   46: invokeinterface 49 5 0
        //   51: pop
        //   52: aload 4
        //   54: invokevirtual 52	android/os/Parcel:readException	()V
        //   57: aload 4
        //   59: invokevirtual 55	android/os/Parcel:recycle	()V
        //   62: aload_3
        //   63: invokevirtual 55	android/os/Parcel:recycle	()V
        //   66: return
        //   67: aconst_null
        //   68: astore_1
        //   69: goto -38 -> 31
        //   72: astore_1
        //   73: aload 4
        //   75: invokevirtual 55	android/os/Parcel:recycle	()V
        //   78: aload_3
        //   79: invokevirtual 55	android/os/Parcel:recycle	()V
        //   82: aload_1
        //   83: athrow
        // Local variable table:
        //   start	length	slot	name	signature
        //   0	84	0	this	zza
        //   0	84	1	paramString	String
        //   0	84	2	paramzzbja	zzbja
        //   3	76	3	localParcel1	Parcel
        //   7	67	4	localParcel2	Parcel
        // Exception table:
        //   from	to	target	type
        //   9	20	72	finally
        //   24	31	72	finally
        //   31	57	72	finally
      }
      
      /* Error */
      public void zze(String paramString1, String paramString2, zzbja paramzzbja)
        throws RemoteException
      {
        // Byte code:
        //   0: invokestatic 30	android/os/Parcel:obtain	()Landroid/os/Parcel;
        //   3: astore 4
        //   5: invokestatic 30	android/os/Parcel:obtain	()Landroid/os/Parcel;
        //   8: astore 5
        //   10: aload 4
        //   12: ldc 32
        //   14: invokevirtual 36	android/os/Parcel:writeInterfaceToken	(Ljava/lang/String;)V
        //   17: aload 4
        //   19: aload_1
        //   20: invokevirtual 71	android/os/Parcel:writeString	(Ljava/lang/String;)V
        //   23: aload 4
        //   25: aload_2
        //   26: invokevirtual 71	android/os/Parcel:writeString	(Ljava/lang/String;)V
        //   29: aload_3
        //   30: ifnull +49 -> 79
        //   33: aload_3
        //   34: invokeinterface 40 1 0
        //   39: astore_1
        //   40: aload 4
        //   42: aload_1
        //   43: invokevirtual 43	android/os/Parcel:writeStrongBinder	(Landroid/os/IBinder;)V
        //   46: aload_0
        //   47: getfield 18	com/google/android/gms/internal/zzbjb$zza$zza:zzrp	Landroid/os/IBinder;
        //   50: bipush 14
        //   52: aload 4
        //   54: aload 5
        //   56: iconst_0
        //   57: invokeinterface 49 5 0
        //   62: pop
        //   63: aload 5
        //   65: invokevirtual 52	android/os/Parcel:readException	()V
        //   68: aload 5
        //   70: invokevirtual 55	android/os/Parcel:recycle	()V
        //   73: aload 4
        //   75: invokevirtual 55	android/os/Parcel:recycle	()V
        //   78: return
        //   79: aconst_null
        //   80: astore_1
        //   81: goto -41 -> 40
        //   84: astore_1
        //   85: aload 5
        //   87: invokevirtual 55	android/os/Parcel:recycle	()V
        //   90: aload 4
        //   92: invokevirtual 55	android/os/Parcel:recycle	()V
        //   95: aload_1
        //   96: athrow
        // Local variable table:
        //   start	length	slot	name	signature
        //   0	97	0	this	zza
        //   0	97	1	paramString1	String
        //   0	97	2	paramString2	String
        //   0	97	3	paramzzbja	zzbja
        //   3	88	4	localParcel1	Parcel
        //   8	78	5	localParcel2	Parcel
        // Exception table:
        //   from	to	target	type
        //   10	29	84	finally
        //   33	40	84	finally
        //   40	68	84	finally
      }
      
      /* Error */
      public void zzf(String paramString, zzbja paramzzbja)
        throws RemoteException
      {
        // Byte code:
        //   0: invokestatic 30	android/os/Parcel:obtain	()Landroid/os/Parcel;
        //   3: astore_3
        //   4: invokestatic 30	android/os/Parcel:obtain	()Landroid/os/Parcel;
        //   7: astore 4
        //   9: aload_3
        //   10: ldc 32
        //   12: invokevirtual 36	android/os/Parcel:writeInterfaceToken	(Ljava/lang/String;)V
        //   15: aload_3
        //   16: aload_1
        //   17: invokevirtual 71	android/os/Parcel:writeString	(Ljava/lang/String;)V
        //   20: aload_2
        //   21: ifnull +46 -> 67
        //   24: aload_2
        //   25: invokeinterface 40 1 0
        //   30: astore_1
        //   31: aload_3
        //   32: aload_1
        //   33: invokevirtual 43	android/os/Parcel:writeStrongBinder	(Landroid/os/IBinder;)V
        //   36: aload_0
        //   37: getfield 18	com/google/android/gms/internal/zzbjb$zza$zza:zzrp	Landroid/os/IBinder;
        //   40: bipush 15
        //   42: aload_3
        //   43: aload 4
        //   45: iconst_0
        //   46: invokeinterface 49 5 0
        //   51: pop
        //   52: aload 4
        //   54: invokevirtual 52	android/os/Parcel:readException	()V
        //   57: aload 4
        //   59: invokevirtual 55	android/os/Parcel:recycle	()V
        //   62: aload_3
        //   63: invokevirtual 55	android/os/Parcel:recycle	()V
        //   66: return
        //   67: aconst_null
        //   68: astore_1
        //   69: goto -38 -> 31
        //   72: astore_1
        //   73: aload 4
        //   75: invokevirtual 55	android/os/Parcel:recycle	()V
        //   78: aload_3
        //   79: invokevirtual 55	android/os/Parcel:recycle	()V
        //   82: aload_1
        //   83: athrow
        // Local variable table:
        //   start	length	slot	name	signature
        //   0	84	0	this	zza
        //   0	84	1	paramString	String
        //   0	84	2	paramzzbja	zzbja
        //   3	76	3	localParcel1	Parcel
        //   7	67	4	localParcel2	Parcel
        // Exception table:
        //   from	to	target	type
        //   9	20	72	finally
        //   24	31	72	finally
        //   31	57	72	finally
      }
      
      /* Error */
      public void zzf(String paramString1, String paramString2, zzbja paramzzbja)
        throws RemoteException
      {
        // Byte code:
        //   0: invokestatic 30	android/os/Parcel:obtain	()Landroid/os/Parcel;
        //   3: astore 4
        //   5: invokestatic 30	android/os/Parcel:obtain	()Landroid/os/Parcel;
        //   8: astore 5
        //   10: aload 4
        //   12: ldc 32
        //   14: invokevirtual 36	android/os/Parcel:writeInterfaceToken	(Ljava/lang/String;)V
        //   17: aload 4
        //   19: aload_1
        //   20: invokevirtual 71	android/os/Parcel:writeString	(Ljava/lang/String;)V
        //   23: aload 4
        //   25: aload_2
        //   26: invokevirtual 71	android/os/Parcel:writeString	(Ljava/lang/String;)V
        //   29: aload_3
        //   30: ifnull +49 -> 79
        //   33: aload_3
        //   34: invokeinterface 40 1 0
        //   39: astore_1
        //   40: aload 4
        //   42: aload_1
        //   43: invokevirtual 43	android/os/Parcel:writeStrongBinder	(Landroid/os/IBinder;)V
        //   46: aload_0
        //   47: getfield 18	com/google/android/gms/internal/zzbjb$zza$zza:zzrp	Landroid/os/IBinder;
        //   50: bipush 21
        //   52: aload 4
        //   54: aload 5
        //   56: iconst_0
        //   57: invokeinterface 49 5 0
        //   62: pop
        //   63: aload 5
        //   65: invokevirtual 52	android/os/Parcel:readException	()V
        //   68: aload 5
        //   70: invokevirtual 55	android/os/Parcel:recycle	()V
        //   73: aload 4
        //   75: invokevirtual 55	android/os/Parcel:recycle	()V
        //   78: return
        //   79: aconst_null
        //   80: astore_1
        //   81: goto -41 -> 40
        //   84: astore_1
        //   85: aload 5
        //   87: invokevirtual 55	android/os/Parcel:recycle	()V
        //   90: aload 4
        //   92: invokevirtual 55	android/os/Parcel:recycle	()V
        //   95: aload_1
        //   96: athrow
        // Local variable table:
        //   start	length	slot	name	signature
        //   0	97	0	this	zza
        //   0	97	1	paramString1	String
        //   0	97	2	paramString2	String
        //   0	97	3	paramzzbja	zzbja
        //   3	88	4	localParcel1	Parcel
        //   8	78	5	localParcel2	Parcel
        // Exception table:
        //   from	to	target	type
        //   10	29	84	finally
        //   33	40	84	finally
        //   40	68	84	finally
      }
      
      /* Error */
      public void zzg(String paramString, zzbja paramzzbja)
        throws RemoteException
      {
        // Byte code:
        //   0: invokestatic 30	android/os/Parcel:obtain	()Landroid/os/Parcel;
        //   3: astore_3
        //   4: invokestatic 30	android/os/Parcel:obtain	()Landroid/os/Parcel;
        //   7: astore 4
        //   9: aload_3
        //   10: ldc 32
        //   12: invokevirtual 36	android/os/Parcel:writeInterfaceToken	(Ljava/lang/String;)V
        //   15: aload_3
        //   16: aload_1
        //   17: invokevirtual 71	android/os/Parcel:writeString	(Ljava/lang/String;)V
        //   20: aload_2
        //   21: ifnull +46 -> 67
        //   24: aload_2
        //   25: invokeinterface 40 1 0
        //   30: astore_1
        //   31: aload_3
        //   32: aload_1
        //   33: invokevirtual 43	android/os/Parcel:writeStrongBinder	(Landroid/os/IBinder;)V
        //   36: aload_0
        //   37: getfield 18	com/google/android/gms/internal/zzbjb$zza$zza:zzrp	Landroid/os/IBinder;
        //   40: bipush 17
        //   42: aload_3
        //   43: aload 4
        //   45: iconst_0
        //   46: invokeinterface 49 5 0
        //   51: pop
        //   52: aload 4
        //   54: invokevirtual 52	android/os/Parcel:readException	()V
        //   57: aload 4
        //   59: invokevirtual 55	android/os/Parcel:recycle	()V
        //   62: aload_3
        //   63: invokevirtual 55	android/os/Parcel:recycle	()V
        //   66: return
        //   67: aconst_null
        //   68: astore_1
        //   69: goto -38 -> 31
        //   72: astore_1
        //   73: aload 4
        //   75: invokevirtual 55	android/os/Parcel:recycle	()V
        //   78: aload_3
        //   79: invokevirtual 55	android/os/Parcel:recycle	()V
        //   82: aload_1
        //   83: athrow
        // Local variable table:
        //   start	length	slot	name	signature
        //   0	84	0	this	zza
        //   0	84	1	paramString	String
        //   0	84	2	paramzzbja	zzbja
        //   3	76	3	localParcel1	Parcel
        //   7	67	4	localParcel2	Parcel
        // Exception table:
        //   from	to	target	type
        //   9	20	72	finally
        //   24	31	72	finally
        //   31	57	72	finally
      }
      
      /* Error */
      public void zzh(String paramString, zzbja paramzzbja)
        throws RemoteException
      {
        // Byte code:
        //   0: invokestatic 30	android/os/Parcel:obtain	()Landroid/os/Parcel;
        //   3: astore_3
        //   4: invokestatic 30	android/os/Parcel:obtain	()Landroid/os/Parcel;
        //   7: astore 4
        //   9: aload_3
        //   10: ldc 32
        //   12: invokevirtual 36	android/os/Parcel:writeInterfaceToken	(Ljava/lang/String;)V
        //   15: aload_3
        //   16: aload_1
        //   17: invokevirtual 71	android/os/Parcel:writeString	(Ljava/lang/String;)V
        //   20: aload_2
        //   21: ifnull +46 -> 67
        //   24: aload_2
        //   25: invokeinterface 40 1 0
        //   30: astore_1
        //   31: aload_3
        //   32: aload_1
        //   33: invokevirtual 43	android/os/Parcel:writeStrongBinder	(Landroid/os/IBinder;)V
        //   36: aload_0
        //   37: getfield 18	com/google/android/gms/internal/zzbjb$zza$zza:zzrp	Landroid/os/IBinder;
        //   40: bipush 18
        //   42: aload_3
        //   43: aload 4
        //   45: iconst_0
        //   46: invokeinterface 49 5 0
        //   51: pop
        //   52: aload 4
        //   54: invokevirtual 52	android/os/Parcel:readException	()V
        //   57: aload 4
        //   59: invokevirtual 55	android/os/Parcel:recycle	()V
        //   62: aload_3
        //   63: invokevirtual 55	android/os/Parcel:recycle	()V
        //   66: return
        //   67: aconst_null
        //   68: astore_1
        //   69: goto -38 -> 31
        //   72: astore_1
        //   73: aload 4
        //   75: invokevirtual 55	android/os/Parcel:recycle	()V
        //   78: aload_3
        //   79: invokevirtual 55	android/os/Parcel:recycle	()V
        //   82: aload_1
        //   83: athrow
        // Local variable table:
        //   start	length	slot	name	signature
        //   0	84	0	this	zza
        //   0	84	1	paramString	String
        //   0	84	2	paramzzbja	zzbja
        //   3	76	3	localParcel1	Parcel
        //   7	67	4	localParcel2	Parcel
        // Exception table:
        //   from	to	target	type
        //   9	20	72	finally
        //   24	31	72	finally
        //   31	57	72	finally
      }
      
      /* Error */
      public void zzi(String paramString, zzbja paramzzbja)
        throws RemoteException
      {
        // Byte code:
        //   0: invokestatic 30	android/os/Parcel:obtain	()Landroid/os/Parcel;
        //   3: astore_3
        //   4: invokestatic 30	android/os/Parcel:obtain	()Landroid/os/Parcel;
        //   7: astore 4
        //   9: aload_3
        //   10: ldc 32
        //   12: invokevirtual 36	android/os/Parcel:writeInterfaceToken	(Ljava/lang/String;)V
        //   15: aload_3
        //   16: aload_1
        //   17: invokevirtual 71	android/os/Parcel:writeString	(Ljava/lang/String;)V
        //   20: aload_2
        //   21: ifnull +46 -> 67
        //   24: aload_2
        //   25: invokeinterface 40 1 0
        //   30: astore_1
        //   31: aload_3
        //   32: aload_1
        //   33: invokevirtual 43	android/os/Parcel:writeStrongBinder	(Landroid/os/IBinder;)V
        //   36: aload_0
        //   37: getfield 18	com/google/android/gms/internal/zzbjb$zza$zza:zzrp	Landroid/os/IBinder;
        //   40: bipush 19
        //   42: aload_3
        //   43: aload 4
        //   45: iconst_0
        //   46: invokeinterface 49 5 0
        //   51: pop
        //   52: aload 4
        //   54: invokevirtual 52	android/os/Parcel:readException	()V
        //   57: aload 4
        //   59: invokevirtual 55	android/os/Parcel:recycle	()V
        //   62: aload_3
        //   63: invokevirtual 55	android/os/Parcel:recycle	()V
        //   66: return
        //   67: aconst_null
        //   68: astore_1
        //   69: goto -38 -> 31
        //   72: astore_1
        //   73: aload 4
        //   75: invokevirtual 55	android/os/Parcel:recycle	()V
        //   78: aload_3
        //   79: invokevirtual 55	android/os/Parcel:recycle	()V
        //   82: aload_1
        //   83: athrow
        // Local variable table:
        //   start	length	slot	name	signature
        //   0	84	0	this	zza
        //   0	84	1	paramString	String
        //   0	84	2	paramzzbja	zzbja
        //   3	76	3	localParcel1	Parcel
        //   7	67	4	localParcel2	Parcel
        // Exception table:
        //   from	to	target	type
        //   9	20	72	finally
        //   24	31	72	finally
        //   31	57	72	finally
      }
      
      /* Error */
      public void zzj(String paramString, zzbja paramzzbja)
        throws RemoteException
      {
        // Byte code:
        //   0: invokestatic 30	android/os/Parcel:obtain	()Landroid/os/Parcel;
        //   3: astore_3
        //   4: invokestatic 30	android/os/Parcel:obtain	()Landroid/os/Parcel;
        //   7: astore 4
        //   9: aload_3
        //   10: ldc 32
        //   12: invokevirtual 36	android/os/Parcel:writeInterfaceToken	(Ljava/lang/String;)V
        //   15: aload_3
        //   16: aload_1
        //   17: invokevirtual 71	android/os/Parcel:writeString	(Ljava/lang/String;)V
        //   20: aload_2
        //   21: ifnull +46 -> 67
        //   24: aload_2
        //   25: invokeinterface 40 1 0
        //   30: astore_1
        //   31: aload_3
        //   32: aload_1
        //   33: invokevirtual 43	android/os/Parcel:writeStrongBinder	(Landroid/os/IBinder;)V
        //   36: aload_0
        //   37: getfield 18	com/google/android/gms/internal/zzbjb$zza$zza:zzrp	Landroid/os/IBinder;
        //   40: bipush 20
        //   42: aload_3
        //   43: aload 4
        //   45: iconst_0
        //   46: invokeinterface 49 5 0
        //   51: pop
        //   52: aload 4
        //   54: invokevirtual 52	android/os/Parcel:readException	()V
        //   57: aload 4
        //   59: invokevirtual 55	android/os/Parcel:recycle	()V
        //   62: aload_3
        //   63: invokevirtual 55	android/os/Parcel:recycle	()V
        //   66: return
        //   67: aconst_null
        //   68: astore_1
        //   69: goto -38 -> 31
        //   72: astore_1
        //   73: aload 4
        //   75: invokevirtual 55	android/os/Parcel:recycle	()V
        //   78: aload_3
        //   79: invokevirtual 55	android/os/Parcel:recycle	()V
        //   82: aload_1
        //   83: athrow
        // Local variable table:
        //   start	length	slot	name	signature
        //   0	84	0	this	zza
        //   0	84	1	paramString	String
        //   0	84	2	paramzzbja	zzbja
        //   3	76	3	localParcel1	Parcel
        //   7	67	4	localParcel2	Parcel
        // Exception table:
        //   from	to	target	type
        //   9	20	72	finally
        //   24	31	72	finally
        //   31	57	72	finally
      }
    }
  }
}


/* Location:              H:\As A Bussines Man\confedince\App Dev Department\What's Fatora\Tawseel APK\Client\dex2jar-2.0\t-dex2jar.jar!\com\google\android\gms\internal\zzbjb.class
 * Java compiler version: 6 (50.0)
 * JD-Core Version:       0.7.1
 */