package com.google.firebase.database.connection.idl;

import android.os.Binder;
import android.os.IBinder;
import android.os.IInterface;
import android.os.Parcel;
import android.os.RemoteException;

public abstract interface zzj
  extends IInterface
{
  public abstract String zzVM()
    throws RemoteException;
  
  public abstract boolean zzVN()
    throws RemoteException;
  
  public abstract zza zzWw()
    throws RemoteException;
  
  public static abstract class zza
    extends Binder
    implements zzj
  {
    public zza()
    {
      attachInterface(this, "com.google.firebase.database.connection.idl.IListenHashProvider");
    }
    
    public static zzj zzfI(IBinder paramIBinder)
    {
      if (paramIBinder == null) {
        return null;
      }
      IInterface localIInterface = paramIBinder.queryLocalInterface("com.google.firebase.database.connection.idl.IListenHashProvider");
      if ((localIInterface != null) && ((localIInterface instanceof zzj))) {
        return (zzj)localIInterface;
      }
      return new zza(paramIBinder);
    }
    
    public IBinder asBinder()
    {
      return this;
    }
    
    public boolean onTransact(int paramInt1, Parcel paramParcel1, Parcel paramParcel2, int paramInt2)
      throws RemoteException
    {
      int i = 0;
      switch (paramInt1)
      {
      default: 
        return super.onTransact(paramInt1, paramParcel1, paramParcel2, paramInt2);
      case 1598968902: 
        paramParcel2.writeString("com.google.firebase.database.connection.idl.IListenHashProvider");
        return true;
      case 1: 
        paramParcel1.enforceInterface("com.google.firebase.database.connection.idl.IListenHashProvider");
        paramParcel1 = zzVM();
        paramParcel2.writeNoException();
        paramParcel2.writeString(paramParcel1);
        return true;
      case 2: 
        paramParcel1.enforceInterface("com.google.firebase.database.connection.idl.IListenHashProvider");
        boolean bool = zzVN();
        paramParcel2.writeNoException();
        paramInt1 = i;
        if (bool) {
          paramInt1 = 1;
        }
        paramParcel2.writeInt(paramInt1);
        return true;
      }
      paramParcel1.enforceInterface("com.google.firebase.database.connection.idl.IListenHashProvider");
      paramParcel1 = zzWw();
      paramParcel2.writeNoException();
      if (paramParcel1 != null)
      {
        paramParcel2.writeInt(1);
        paramParcel1.writeToParcel(paramParcel2, 1);
        return true;
      }
      paramParcel2.writeInt(0);
      return true;
    }
    
    private static class zza
      implements zzj
    {
      private IBinder zzrp;
      
      zza(IBinder paramIBinder)
      {
        this.zzrp = paramIBinder;
      }
      
      public IBinder asBinder()
      {
        return this.zzrp;
      }
      
      public String zzVM()
        throws RemoteException
      {
        Parcel localParcel1 = Parcel.obtain();
        Parcel localParcel2 = Parcel.obtain();
        try
        {
          localParcel1.writeInterfaceToken("com.google.firebase.database.connection.idl.IListenHashProvider");
          this.zzrp.transact(1, localParcel1, localParcel2, 0);
          localParcel2.readException();
          String str = localParcel2.readString();
          return str;
        }
        finally
        {
          localParcel2.recycle();
          localParcel1.recycle();
        }
      }
      
      public boolean zzVN()
        throws RemoteException
      {
        boolean bool = false;
        Parcel localParcel1 = Parcel.obtain();
        Parcel localParcel2 = Parcel.obtain();
        try
        {
          localParcel1.writeInterfaceToken("com.google.firebase.database.connection.idl.IListenHashProvider");
          this.zzrp.transact(2, localParcel1, localParcel2, 0);
          localParcel2.readException();
          int i = localParcel2.readInt();
          if (i != 0) {
            bool = true;
          }
          return bool;
        }
        finally
        {
          localParcel2.recycle();
          localParcel1.recycle();
        }
      }
      
      /* Error */
      public zza zzWw()
        throws RemoteException
      {
        // Byte code:
        //   0: invokestatic 31	android/os/Parcel:obtain	()Landroid/os/Parcel;
        //   3: astore_2
        //   4: invokestatic 31	android/os/Parcel:obtain	()Landroid/os/Parcel;
        //   7: astore_3
        //   8: aload_2
        //   9: ldc 33
        //   11: invokevirtual 37	android/os/Parcel:writeInterfaceToken	(Ljava/lang/String;)V
        //   14: aload_0
        //   15: getfield 18	com/google/firebase/database/connection/idl/zzj$zza$zza:zzrp	Landroid/os/IBinder;
        //   18: iconst_3
        //   19: aload_2
        //   20: aload_3
        //   21: iconst_0
        //   22: invokeinterface 43 5 0
        //   27: pop
        //   28: aload_3
        //   29: invokevirtual 46	android/os/Parcel:readException	()V
        //   32: aload_3
        //   33: invokevirtual 59	android/os/Parcel:readInt	()I
        //   36: ifeq +26 -> 62
        //   39: getstatic 67	com/google/firebase/database/connection/idl/zza:CREATOR	Landroid/os/Parcelable$Creator;
        //   42: aload_3
        //   43: invokeinterface 73 2 0
        //   48: checkcast 63	com/google/firebase/database/connection/idl/zza
        //   51: astore_1
        //   52: aload_3
        //   53: invokevirtual 52	android/os/Parcel:recycle	()V
        //   56: aload_2
        //   57: invokevirtual 52	android/os/Parcel:recycle	()V
        //   60: aload_1
        //   61: areturn
        //   62: aconst_null
        //   63: astore_1
        //   64: goto -12 -> 52
        //   67: astore_1
        //   68: aload_3
        //   69: invokevirtual 52	android/os/Parcel:recycle	()V
        //   72: aload_2
        //   73: invokevirtual 52	android/os/Parcel:recycle	()V
        //   76: aload_1
        //   77: athrow
        // Local variable table:
        //   start	length	slot	name	signature
        //   0	78	0	this	zza
        //   51	13	1	localzza	zza
        //   67	10	1	localObject	Object
        //   3	70	2	localParcel1	Parcel
        //   7	62	3	localParcel2	Parcel
        // Exception table:
        //   from	to	target	type
        //   8	52	67	finally
      }
    }
  }
}


/* Location:              H:\As A Bussines Man\confedince\App Dev Department\What's Fatora\Tawseel APK\Client\dex2jar-2.0\t-dex2jar.jar!\com\google\firebase\database\connection\idl\zzj.class
 * Java compiler version: 6 (50.0)
 * JD-Core Version:       0.7.1
 */