package com.google.android.gms.internal;

import java.io.IOException;
import java.sql.Date;
import java.text.DateFormat;
import java.text.SimpleDateFormat;

public final class zzbtd
  extends zzbsd<Date>
{
  public static final zzbse zzcnX = new zzbse()
  {
    public <T> zzbsd<T> zza(zzbrl paramAnonymouszzbrl, zzbth<T> paramAnonymouszzbth)
    {
      if (paramAnonymouszzbth.zzacb() == Date.class) {
        return new zzbtd();
      }
      return null;
    }
  };
  private final DateFormat zzcox = new SimpleDateFormat("MMM d, yyyy");
  
  public void zza(zzbtk paramzzbtk, Date paramDate)
    throws IOException
  {
    if (paramDate == null) {}
    for (paramDate = null;; paramDate = this.zzcox.format(paramDate)) {
      try
      {
        paramzzbtk.zzjX(paramDate);
        return;
      }
      finally {}
    }
  }
  
  /* Error */
  public Date zzm(zzbti paramzzbti)
    throws IOException
  {
    // Byte code:
    //   0: aload_0
    //   1: monitorenter
    //   2: aload_1
    //   3: invokevirtual 65	com/google/android/gms/internal/zzbti:zzabQ	()Lcom/google/android/gms/internal/zzbtj;
    //   6: getstatic 71	com/google/android/gms/internal/zzbtj:zzcqa	Lcom/google/android/gms/internal/zzbtj;
    //   9: if_acmpne +13 -> 22
    //   12: aload_1
    //   13: invokevirtual 74	com/google/android/gms/internal/zzbti:nextNull	()V
    //   16: aconst_null
    //   17: astore_1
    //   18: aload_0
    //   19: monitorexit
    //   20: aload_1
    //   21: areturn
    //   22: new 35	java/sql/Date
    //   25: dup
    //   26: aload_0
    //   27: getfield 29	com/google/android/gms/internal/zzbtd:zzcox	Ljava/text/DateFormat;
    //   30: aload_1
    //   31: invokevirtual 78	com/google/android/gms/internal/zzbti:nextString	()Ljava/lang/String;
    //   34: invokevirtual 82	java/text/DateFormat:parse	(Ljava/lang/String;)Ljava/util/Date;
    //   37: invokevirtual 88	java/util/Date:getTime	()J
    //   40: invokespecial 91	java/sql/Date:<init>	(J)V
    //   43: astore_1
    //   44: goto -26 -> 18
    //   47: astore_1
    //   48: new 93	com/google/android/gms/internal/zzbsa
    //   51: dup
    //   52: aload_1
    //   53: invokespecial 96	com/google/android/gms/internal/zzbsa:<init>	(Ljava/lang/Throwable;)V
    //   56: athrow
    //   57: astore_1
    //   58: aload_0
    //   59: monitorexit
    //   60: aload_1
    //   61: athrow
    // Local variable table:
    //   start	length	slot	name	signature
    //   0	62	0	this	zzbtd
    //   0	62	1	paramzzbti	zzbti
    // Exception table:
    //   from	to	target	type
    //   22	44	47	java/text/ParseException
    //   2	16	57	finally
    //   22	44	57	finally
    //   48	57	57	finally
  }
}


/* Location:              H:\As A Bussines Man\confedince\App Dev Department\What's Fatora\Tawseel APK\Client\dex2jar-2.0\t-dex2jar.jar!\com\google\android\gms\internal\zzbtd.class
 * Java compiler version: 6 (50.0)
 * JD-Core Version:       0.7.1
 */